htmlslacker/__init__.py
htmlslacker/htmlslacker.py
html_slacker-0.1.6.dist-info/LICENSE.txt
html_slacker-0.1.6.dist-info/METADATA
html_slacker-0.1.6.dist-info/WHEEL
html_slacker-0.1.6.dist-info/top_level.txt
html_slacker-0.1.6.dist-info/RECORD
