Metadata-Version: 2.1
Name: html-slacker
Version: 0.1.6
Summary: Converts HTML to Slack formatted markdown
Home-page: https://github.com/codex-team/html-slacker
Author: CodeX Team
Author-email: team@ifmo.su
License: MIT
Keywords: slack bot html convert markdown slackbot pythonbot slack html markdown
Platform: UNKNOWN
Classifier: Intended Audience :: Developers
Classifier: Programming Language :: Python
Classifier: License :: OSI Approved :: MIT License
Classifier: Topic :: Software Development :: Libraries
Classifier: Environment :: Console
Requires-Python: >=2.5
